{"file_name": "./CC-MAIN-20200402173940-20200402203940-00200/CC-MAIN-20200402173940-20200402203940-00200.warc.gz", "instructions": "On your iPhone or iPad, open the Chrome app . At the bottom right, tap More . Tap Settings and then Passwords . See, delete, or export a password: See : Tap the saved password. Under \"Password,\" tap Show . Delete : At the top right, tap Edit . Under \"Saved Passwords,\" tap the site you want to remove and then Delete . Export : Scroll down to the bottom, and then tap Export Passwords .", "url": "https://support.google.com/chrome/answer/95606?p=settings_password&rd=1&co=GENIE.Platform%3DiOS", "index": 0}
{"file_name": "./CC-MAIN-20200402173940-20200402203940-00200/CC-MAIN-20200402173940-20200402203940-00200.warc.gz", "instructions": "On your iPhone or iPad, open the Chrome app . At the bottom right, tap More . Tap Settings and then Passwords . Turn Save Passwords on or off.", "url": "https://support.google.com/chrome/answer/95606?p=settings_password&rd=1&co=GENIE.Platform%3DiOS", "index": 1}
{"file_name": "./CC-MAIN-20200402173940-20200402203940-00200/CC-MAIN-20200402173940-20200402203940-00200.warc.gz", "instructions": "On your iPhone or iPad, open the Chrome app . To the right of the address bar, tap More and then Settings . Under \"Account,\" tap Sync and Google services . Turn Warn you if passwords are exposed in a data breach on or off.", "url": "https://support.google.com/chrome/answer/95606?p=settings_password&rd=1&co=GENIE.Platform%3DiOS", "index": 2}
