{"file_name": "./CC-MAIN-20200401192839-20200401222839-00454/CC-MAIN-20200401192839-20200401222839-00454.warc.gz", "instructions": "Tap Settings > Security . Tap Unknown Sources . Tap OK .", "url": "https://www.lifewire.com/how-to-download-showbox-on-android-4770649", "index": 0}
{"file_name": "./CC-MAIN-20200401192839-20200401222839-00454/CC-MAIN-20200401192839-20200401222839-00454.warc.gz", "instructions": "On your phone's web browser, go to https://apkpure.com/ Search for \"Showbox.\" Showbox used to also be referred to as Showbox Lite or Showbox HD. Now, the app is solely known as Showbox. Tap Download APK and wait for the file to download. The speed will vary depending on your internet connection. Tap Open . Tap Install . Tap Done . You've successfully installed Showbox.", "url": "https://www.lifewire.com/how-to-download-showbox-on-android-4770649", "index": 1}
{"file_name": "./CC-MAIN-20200401192839-20200401222839-00454/CC-MAIN-20200401192839-20200401222839-00454.warc.gz", "instructions": "Open the Showbox app to immediately browse movie news. Tap the hamburger menu icon to bring up other options. Tap Movies to browse the movies available on the service. Tap the picture of the movie to open a preview. Tap Watch Now to watch it.", "url": "https://www.lifewire.com/how-to-download-showbox-on-android-4770649", "index": 2}
