{"file_name": "./CC-MAIN-20200329045008-20200329075008-00009/CC-MAIN-20200329045008-20200329075008-00009.warc.gz", "instructions": "Select the text . Don t include any trailing paragraph breaks or punctuation in your selected text. Tap Phonetics. (You may need to tap the Show More Items button until you see the Phonetics button.) A phonetic guide appears with the selected text. To change the phonetic guide text, tap Guide in the Phonetic Guide list, then select other guide text, or type your own in the text field at the top. Tap Close to apply the text and close the phonetic guide.", "url": "https://support.apple.com/guide/keynote-iphone/use-phonetic-guides-tan6142c48af/ios", "index": 0}
{"file_name": "./CC-MAIN-20200329045008-20200329075008-00009/CC-MAIN-20200329045008-20200329075008-00009.warc.gz", "instructions": "Select the word with phonetic guide text, then tap it. Do one of the following: Change the guide text: In the Guide Text list, select guide text in the language you prefer. The phonetic options presented depend on which keyboards are set up. Remove the guide text: Tap Remove Guide.", "url": "https://support.apple.com/guide/keynote-iphone/use-phonetic-guides-tan6142c48af/ios", "index": 1}
