{"file_name": "./CC-MAIN-20200328225036-20200329015036-00114/CC-MAIN-20200328225036-20200329015036-00114.warc.gz", "instructions": "On your Android phone or tablet, open the Google Maps app . Tap Contribute and then View your profile and then Profile settings . Under Profile settings , turn off Show contributions on your profile .", "url": "https://support.google.com/maps/answer/9514690?hl=en-CA&ref_topic=3257381", "index": 0}
{"file_name": "./CC-MAIN-20200328225036-20200329015036-00114/CC-MAIN-20200328225036-20200329015036-00114.warc.gz", "instructions": "On your Android phone or tablet, open the Google Maps app . Tap Contribute and then View your profile and then Profile settings . Under Profile settings , turn on Show contributions on your profile .", "url": "https://support.google.com/maps/answer/9514690?hl=en-CA&ref_topic=3257381", "index": 1}
