{"file_name": "./CC-MAIN-20200410173109-20200410203609-00210/CC-MAIN-20200410173109-20200410203609-00210.warc.gz", "instructions": "On your iPhone or iPad, open the Photos app . At the top, tap a memory. To move to the next or previous photo, tap on the right or left of the screen. To skip to the next or previous memory, swipe right or left on the screen To pause on a photo, touch and hold it.", "url": "https://support.google.com/photos/answer/9454489?co=GENIE.Platform%3DiOS", "index": 0}
{"file_name": "./CC-MAIN-20200410173109-20200410203609-00210/CC-MAIN-20200410173109-20200410203609-00210.warc.gz", "instructions": "On your iPhone or iPad, open the Photos app . Tap Menu and then Settings and then Memories . Turn off Show memories .", "url": "https://support.google.com/photos/answer/9454489?co=GENIE.Platform%3DiOS", "index": 1}
{"file_name": "./CC-MAIN-20200410173109-20200410203609-00210/CC-MAIN-20200410173109-20200410203609-00210.warc.gz", "instructions": "On your iPhone or iPad, open the Photos app . Tap Menu and then Settings and then Memories . Tap People & pets . Choose who you want to hide. Tap Done .", "url": "https://support.google.com/photos/answer/9454489?co=GENIE.Platform%3DiOS", "index": 2}
{"file_name": "./CC-MAIN-20200410173109-20200410203609-00210/CC-MAIN-20200410173109-20200410203609-00210.warc.gz", "instructions": "On your iPhone or iPad, open the Photos app . Tap Menu and then Settings and then Memories . Tap Dates . Add dates you want to hide.", "url": "https://support.google.com/photos/answer/9454489?co=GENIE.Platform%3DiOS", "index": 3}
