{"file_name": "./CC-MAIN-20200404073139-20200404103139-00065/CC-MAIN-20200404073139-20200404103139-00065.warc.gz", "instructions": "In the Safari app on your Mac, navigate to the webpage or PDF you want to save. Click the Share button in the toolbar, then choose Save to Books. If Save to Books isn t listed, click More to add it to the list. On your iPhone or iPad, open Books. Tap Library to see all of your titles. Tap the cover to open the PDF or webpage you saved.", "url": "https://support.apple.com/en-bh/guide/safari/ibrwc6580898/mac", "index": 0}
{"file_name": "./CC-MAIN-20200404073139-20200404103139-00065/CC-MAIN-20200404073139-20200404103139-00065.warc.gz", "instructions": "Make sure your Android phone or tablet is connected to Wi-Fi or your mobile network. On your Android phone or tablet, open the Google Play Movies & TV app . Tap Library . Find the movie or TV episode you d like to download. Tap download . To remove or stop a download in progress, tap Download . To find downloaded videos, tap Menu and then Settings .", "url": "https://support.google.com/googleplay/answer/2851696?hl=en", "index": 0}
{"file_name": "./CC-MAIN-20200404073139-20200404103139-00065/CC-MAIN-20200404073139-20200404103139-00065.warc.gz", "instructions": "On your Android phone or tablet, open the Google Play Movies & TV app . Tap Menu and then Settings and then Downloads and then Network and then Download on any network .", "url": "https://support.google.com/googleplay/answer/2851696?hl=en", "index": 1}
{"file_name": "./CC-MAIN-20200404073139-20200404103139-00065/CC-MAIN-20200404073139-20200404103139-00065.warc.gz", "instructions": "On your Android phone or tablet, open the Google Play Movies & TV app . Next to a downloaded video, tap the red check mark .", "url": "https://support.google.com/googleplay/answer/2851696?hl=en", "index": 2}
